setup.py
data_checker1453/Check.py
data_checker1453/Display.py
data_checker1453/__init__.py
data_checker1453.egg-info/PKG-INFO
data_checker1453.egg-info/SOURCES.txt
data_checker1453.egg-info/dependency_links.txt
data_checker1453.egg-info/not-zip-safe
data_checker1453.egg-info/top_level.txt