Metadata-Version: 2.1
Name: data-checker1453
Version: 0.35
Summary: package to offer basic previews to the data
Home-page: UNKNOWN
Author: Mohamad AlZainy
Author-email: zainy1453@gmail.com
License: UNKNOWN
Platform: UNKNOWN
